setup.py
alicloud_gateway_iot/__init__.py
alicloud_gateway_iot/client.py
alicloud_gateway_iot/models.py
alicloud_gateway_iot_py2.egg-info/PKG-INFO
alicloud_gateway_iot_py2.egg-info/SOURCES.txt
alicloud_gateway_iot_py2.egg-info/dependency_links.txt
alicloud_gateway_iot_py2.egg-info/requires.txt
alicloud_gateway_iot_py2.egg-info/top_level.txt